colmi_r02_client/__init__.py
colmi_r02_client/battery.py
colmi_r02_client/blink_twice.py
colmi_r02_client/cli.py
colmi_r02_client/client.py
colmi_r02_client/hr.py
colmi_r02_client/hr_settings.py
colmi_r02_client/packet.py
colmi_r02_client/real_time_hr.py
colmi_r02_client/set_time.py
colmi_r02_client/steps.py
colmi_r02_client-0.1.0.dist-info/LICENSE
colmi_r02_client-0.1.0.dist-info/METADATA
colmi_r02_client-0.1.0.dist-info/WHEEL
colmi_r02_client-0.1.0.dist-info/entry_points.txt
colmi_r02_client-0.1.0.dist-info/RECORD
