Metadata-Version: 2.1
Name: colmi-r02-client
Version: 0.1.0
Summary: Connect to Colmi R02 smart ring over BLE
Author: Wesley Ellis
Author-email: tahnok@gmail.com
Requires-Python: >=3.11,<3.13
Classifier: Programming Language :: Python :: 3
Classifier: Programming Language :: Python :: 3.11
Classifier: Programming Language :: Python :: 3.12
Requires-Dist: asyncclick (>=8.1.7.2,<9.0.0.0)
Requires-Dist: bleak (>=0.22.2,<0.23.0)
